scm_python_idea/lib/idea.py
scm_python_idea/tapps/idea/common.py
scm_python_idea/tapps/idea/module.py
scm_python_idea/tapps/idea/settings_color.py
scm_python_idea/tapps/idea/settings_keymaps.py
scm_python_idea/tapps/idea/workspace_maven.py
scm_python_idea-0.1.0.dist-info/METADATA
scm_python_idea-0.1.0.dist-info/WHEEL
scm_python_idea-0.1.0.dist-info/top_level.txt
scm_python_idea-0.1.0.dist-info/RECORD
